[
    {
        "pilot_id": "6a4e58ae5760ec7cdb4bd83a",
        "fullname": "Nick Star",
        "avatar": "6a4e58ae5760ec7cdb4bd83a1783608112327",
        "flights": [
            {
                "_id": "6a5483b55760ec7cdbc36b37",
                "aircraft": {
                    "_id": "6988b9149da57b990ad5b53e",
                    "name": "Airbus A320 neo",
                    "customName": "DRY LEASE l free A320neo v2 msfs2024",
                    "icao": "A20N"
                },
                "type": "pax",
                "flightNumber": "2301",
                "free": true,
                "schedule": false,
                "charter": false,
                "payload": {
                    "pax": 174,
                    "cargo": 31,
                    "weights": {
                        "cargo": 2077
                    }
                },
                "depTime": "2026-07-13T06:50:00.000Z",
                "duration": 75,
                "arrTime": "2026-07-13T08:05:00.000Z",
                "depTimeAct": "2026-07-13T06:47:08.014Z",
                "delay": -29,
                "takeoffTimeAct": "2026-07-13T06:56:04.346Z",
                "durationAct": 39,
                "arrTimeAct": "2026-07-13T07:35:30.255Z",
                "open": "2026-07-13T06:31:16.765Z",
                "close": "2026-07-13T07:41:27.173Z",
                "rating": 10,
                "simulator": "msfs",
                "network": {
                    "name": null
                },
                "emergency": false,
                "result": {
                    "totals": {
                        "distance": 215,
                        "fuel": 1430,
                        "expenses": 9000,
                        "penalties": 0,
                        "revenue": 22055,
                        "balance": 13055,
                        "prices": {
                            "ticketPrice": 101,
                            "cargoUnitPrice": 125,
                            "costScalars": {
                                "timeAcceleration": 1,
                                "dep": 1,
                                "arr": 1,
                                "fuel": 1,
                                "ground": 1
                            }
                        },
                        "payload": {
                            "pax": 174,
                            "cargo": 31,
                            "paxByClass": {
                                "F": 0,
                                "C": 6,
                                "Y": 168
                            }
                        }
                    },
                    "expenses": {
                        "fuel": 1617,
                        "aircraft": 4475,
                        "handling": 2278,
                        "landing": 630
                    },
                    "revenue": {
                        "tickets": 18180,
                        "cargo": 3875
                    },
                    "violations": [
                        {
                            "title": "Great touchdown: 1.17G (194 ft/min, normal  conditions)<br/>Distance from threshold: 421m (accepted range: 173-693m)<br/>Average centerline deviation: 0.64m<br/>Max centerline deviation: 2.16m",
                            "penalty": {
                                "points": 0,
                                "cash": 0
                            },
                            "entry": {
                                "type": "landing",
                                "payload": {
                                    "system": {
                                        "fps": 23
                                    },
                                    "touchDown": {
                                        "gForce": 1.17,
                                        "rate": 194
                                    },
                                    "weather": {
                                        "windDir": 290.05,
                                        "windSpd": 3.32,
                                        "windX": -2.12
                                    }
                                }
                            }
                        }
                    ]
                },
                "createdAt": "2026-07-13T06:20:37.384Z",
                "updatedAt": "2026-07-13T07:41:27.242Z",
                "dep": {
                    "icao": "ENGM",
                    "name": "Oslo Airport, Gardermoen",
                    "city": "Oslo (Gardermoen)",
                    "location": {
                        "lat": 60.193901,
                        "lon": 11.1004,
                        "elev": 681
                    }
                },
                "arr": {
                    "icao": "ENKB",
                    "name": "Kristiansund Airport, Kvernberget",
                    "city": "Kvernberget",
                    "location": {
                        "lat": 63.111801,
                        "lon": 7.82452,
                        "elev": 204
                    }
                },
                "actArr": {
                    "icao": "ENKB",
                    "name": "Kristiansund Airport, Kvernberget",
                    "city": "Kvernberget",
                    "location": {
                        "lat": 63.111801,
                        "lon": 7.82452,
                        "elev": 204
                    }
                }
            },
            {
                "_id": "6a54999a5760ec7cdbc45675",
                "aircraft": {
                    "_id": "6988b9149da57b990ad5b53e",
                    "name": "Airbus A320 neo",
                    "customName": "DRY LEASE l free A320neo v2 msfs2024",
                    "icao": "A20N"
                },
                "type": "pax",
                "flightNumber": "2304",
                "free": true,
                "schedule": false,
                "charter": false,
                "payload": {
                    "pax": 174,
                    "cargo": 22,
                    "weights": {
                        "cargo": 2200
                    }
                },
                "depTime": "2026-07-13T08:25:00.000Z",
                "duration": 75,
                "arrTime": "2026-07-13T09:40:00.000Z",
                "depTimeAct": "2026-07-13T08:18:52.027Z",
                "delay": -34,
                "takeoffTimeAct": "2026-07-13T08:24:32.107Z",
                "durationAct": 42,
                "arrTimeAct": "2026-07-13T09:06:19.921Z",
                "open": "2026-07-13T08:01:28.439Z",
                "close": "2026-07-13T09:10:00.944Z",
                "rating": 10,
                "simulator": "msfs",
                "network": {
                    "name": null
                },
                "emergency": false,
                "result": {
                    "totals": {
                        "distance": 245,
                        "fuel": 1464,
                        "expenses": 8827,
                        "penalties": 0,
                        "revenue": 20930,
                        "balance": 12103,
                        "prices": {
                            "ticketPrice": 101,
                            "cargoUnitPrice": 125,
                            "costScalars": {
                                "timeAcceleration": 1,
                                "dep": 1,
                                "arr": 1,
                                "fuel": 1,
                                "ground": 1
                            }
                        },
                        "payload": {
                            "pax": 174,
                            "cargo": 22,
                            "paxByClass": {
                                "F": 0,
                                "C": 6,
                                "Y": 168
                            }
                        }
                    },
                    "expenses": {
                        "fuel": 1656,
                        "aircraft": 4550,
                        "handling": 881,
                        "landing": 1740
                    },
                    "revenue": {
                        "tickets": 18180,
                        "cargo": 2750
                    },
                    "violations": [
                        {
                            "title": "Great touchdown: 1.09G (100 ft/min, normal  conditions)<br/>Distance from threshold: 462m (accepted range: 201-808m)<br/>Average centerline deviation: 1.00m<br/>Max centerline deviation: 1.38m",
                            "penalty": {
                                "points": 0,
                                "cash": 0
                            },
                            "entry": {
                                "type": "landing",
                                "payload": {
                                    "system": {
                                        "fps": 22
                                    },
                                    "touchDown": {
                                        "gForce": 1.09,
                                        "rate": 100
                                    },
                                    "weather": {
                                        "windDir": 63.43,
                                        "windSpd": 3.09,
                                        "windX": 2.24
                                    }
                                }
                            }
                        }
                    ]
                },
                "createdAt": "2026-07-13T07:54:02.051Z",
                "updatedAt": "2026-07-13T09:10:01.032Z",
                "dep": {
                    "icao": "ENKB",
                    "name": "Kristiansund Airport, Kvernberget",
                    "city": "Kvernberget",
                    "location": {
                        "lat": 63.111801,
                        "lon": 7.82452,
                        "elev": 204
                    }
                },
                "arr": {
                    "icao": "ENGM",
                    "name": "Oslo Airport, Gardermoen",
                    "city": "Oslo (Gardermoen)",
                    "location": {
                        "lat": 60.193901,
                        "lon": 11.1004,
                        "elev": 681
                    }
                },
                "actArr": {
                    "icao": "ENGM",
                    "name": "Oslo Airport, Gardermoen",
                    "city": "Oslo (Gardermoen)",
                    "location": {
                        "lat": 60.193901,
                        "lon": 11.1004,
                        "elev": 681
                    }
                }
            }
        ]
    },
    {
        "pilot_id": "69db5c78997a4751ff8a1806",
        "fullname": "Mozhehov Denys",
        "avatar": "69db5c78997a4751ff8a18061776021637900",
        "flights": [
            {
                "_id": "6a547e6c5760ec7cdbc32fc5",
                "aircraft": {
                    "_id": "695ebf3c3dc76275ba3e31f1",
                    "name": "Boeing 777-300ER",
                    "customName": "SkyLine Express l 777-300ER based in UKBB l UR-AZR",
                    "icao": "B77W"
                },
                "type": "pax",
                "flightNumber": "217D",
                "free": false,
                "schedule": false,
                "charter": true,
                "payload": {
                    "pax": 531,
                    "cargo": 0,
                    "weights": {
                        "cargo": 0
                    }
                },
                "depTime": "2026-07-13T06:12:00.000Z",
                "duration": 95,
                "arrTime": "2026-07-13T07:47:00.000Z",
                "depTimeAct": "2026-07-13T06:04:39.919Z",
                "delay": -4,
                "takeoffTimeAct": "2026-07-13T06:04:50.927Z",
                "durationAct": 98,
                "arrTimeAct": "2026-07-13T07:42:49.111Z",
                "open": "2026-07-13T06:04:10.774Z",
                "close": "2026-07-13T07:45:38.147Z",
                "rating": 9.97,
                "simulator": "msfs",
                "network": {
                    "name": null
                },
                "emergency": false,
                "result": {
                    "totals": {
                        "distance": 582,
                        "fuel": 13287,
                        "expenses": 41711,
                        "penalties": 0,
                        "revenue": 95049,
                        "balance": 53338,
                        "prices": {
                            "ticketPrice": 179,
                            "cargoUnitPrice": 208,
                            "costScalars": {
                                "timeAcceleration": 1,
                                "dep": 0.9,
                                "arr": 0.9,
                                "fuel": 1,
                                "ground": 0.9
                            }
                        },
                        "payload": {
                            "pax": 531,
                            "cargo": 0,
                            "paxByClass": {
                                "F": 0,
                                "C": 0,
                                "Y": 531
                            }
                        }
                    },
                    "expenses": {
                        "fuel": 15021,
                        "aircraft": 18630,
                        "handling": 2390,
                        "landing": 5670
                    },
                    "revenue": {
                        "tickets": 95049,
                        "cargo": 0
                    },
                    "violations": [
                        {
                            "title": "Average touchdown: 1.41G (289 ft/min, normal  conditions)<br/>Distance from threshold: 348m (accepted range: 209-838m)<br/>Average centerline deviation: 0.83m<br/>Max centerline deviation: 2.19m",
                            "penalty": {
                                "points": -3,
                                "cash": 0
                            },
                            "entry": {
                                "type": "landing",
                                "payload": {
                                    "system": {
                                        "fps": 31
                                    },
                                    "touchDown": {
                                        "gForce": 1.41,
                                        "rate": 289
                                    },
                                    "weather": {
                                        "windDir": 270.08,
                                        "windSpd": 1.1,
                                        "windX": -0.3
                                    }
                                }
                            }
                        }
                    ]
                },
                "createdAt": "2026-07-13T05:58:04.031Z",
                "updatedAt": "2026-07-13T07:45:38.232Z",
                "dep": {
                    "icao": "LDSP",
                    "name": "Split Airport",
                    "city": "Kaštel Štafilić",
                    "location": {
                        "lat": 43.538898,
                        "lon": 16.298,
                        "elev": 79
                    }
                },
                "arr": {
                    "icao": "EDDF",
                    "name": "Frankfurt Airport",
                    "city": "Frankfurt am Main",
                    "location": {
                        "lat": 50.030241,
                        "lon": 8.561096,
                        "elev": 364
                    }
                },
                "actArr": {
                    "icao": "EDDF",
                    "name": "Frankfurt Airport",
                    "city": "Frankfurt am Main",
                    "location": {
                        "lat": 50.030241,
                        "lon": 8.561096,
                        "elev": 364
                    }
                }
            }
        ]
    },
    {
        "pilot_id": "6a4771715760ec7cdbbdf901",
        "fullname": "Saint Helgi",
        "avatar": "6a4771715760ec7cdbbdf9011783534614052",
        "flights": [
            {
                "_id": "6a547dbe5760ec7cdbc3290e",
                "aircraft": {
                    "_id": "695a7ab13dc76275bad3933a",
                    "name": "Boeing 737-800",
                    "customName": "SkyLine Express l 737-800 based in UKDE UKLL l UR-SLG",
                    "icao": "B738"
                },
                "type": "pax",
                "flightNumber": "0210",
                "free": true,
                "schedule": false,
                "charter": false,
                "payload": {
                    "pax": 177,
                    "cargo": 34,
                    "weights": {
                        "cargo": 2686
                    }
                },
                "depTime": "2026-07-13T06:10:00.000Z",
                "duration": 125,
                "arrTime": "2026-07-13T08:15:00.000Z",
                "depTimeAct": "2026-07-13T06:27:55.729Z",
                "delay": 53,
                "takeoffTimeAct": "2026-07-13T07:08:36.411Z",
                "durationAct": 120,
                "arrTimeAct": "2026-07-13T09:08:27.545Z",
                "open": "2026-07-13T06:25:12.156Z",
                "close": "2026-07-13T09:15:21.117Z",
                "rating": 10,
                "simulator": "msfs2024",
                "network": {
                    "name": null
                },
                "emergency": false,
                "result": {
                    "totals": {
                        "distance": 774,
                        "fuel": 5424,
                        "expenses": 12329,
                        "penalties": 265,
                        "revenue": 28253,
                        "balance": 15659,
                        "prices": {
                            "ticketPrice": 131,
                            "cargoUnitPrice": 149,
                            "costScalars": {
                                "timeAcceleration": 1,
                                "dep": 0.7,
                                "arr": 0.9,
                                "fuel": 0.8,
                                "ground": 0.8
                            }
                        },
                        "payload": {
                            "pax": 177,
                            "cargo": 34,
                            "paxByClass": {
                                "F": 0,
                                "C": 0,
                                "Y": 177
                            }
                        }
                    },
                    "expenses": {
                        "fuel": 4906,
                        "aircraft": 5900,
                        "handling": 632,
                        "landing": 891
                    },
                    "revenue": {
                        "tickets": 23187,
                        "cargo": 5066
                    },
                    "violations": [
                        {
                            "title": "Flight delayed 3 minutes (max 15 minutes after scheduled is allowed)",
                            "penalty": {
                                "points": 0,
                                "cash": 265
                            },
                            "entry": {
                                "type": "offblock",
                                "payload": {
                                    "system": {
                                        "fps": 44
                                    }
                                }
                            }
                        },
                        {
                            "title": "Great touchdown: 1.07G (83 ft/min, challenging  conditions)<br/>Distance from threshold: 675m (accepted range: 194-777m)<br/>Average centerline deviation: 0.80m<br/>Max centerline deviation: 1.62m",
                            "penalty": {
                                "points": 0,
                                "cash": 0
                            },
                            "entry": {
                                "type": "landing",
                                "payload": {
                                    "system": {
                                        "fps": 41
                                    },
                                    "touchDown": {
                                        "gForce": 1.07,
                                        "rate": 83
                                    },
                                    "weather": {
                                        "windDir": 340.01,
                                        "windSpd": 18.14,
                                        "windX": -0.15
                                    }
                                }
                            }
                        }
                    ]
                },
                "createdAt": "2026-07-13T05:55:10.277Z",
                "updatedAt": "2026-07-13T09:15:21.211Z",
                "dep": {
                    "icao": "UKOO",
                    "name": "Odessa International Airport",
                    "city": "Odessa",
                    "location": {
                        "lat": 46.4268,
                        "lon": 30.6765,
                        "elev": 172
                    }
                },
                "arr": {
                    "icao": "EVRA",
                    "name": "Riga International Airport",
                    "city": "Riga",
                    "location": {
                        "lat": 56.920752,
                        "lon": 23.970711,
                        "elev": 36
                    }
                },
                "actArr": {
                    "icao": "EVRA",
                    "name": "Riga International Airport",
                    "city": "Riga",
                    "location": {
                        "lat": 56.920752,
                        "lon": 23.970711,
                        "elev": 36
                    }
                }
            }
        ]
    },
    {
        "pilot_id": "69778f513dc76275bad73f10",
        "fullname": "Puero Dim",
        "avatar": "69778f513dc76275bad73f101778437215285",
        "flights": [
            {
                "_id": "6a548f235760ec7cdbc3e05d",
                "aircraft": {
                    "_id": "696285163dc76275ba9ef60c",
                    "name": "Boeing 737-800",
                    "customName": "UCAA l 737-800 (pax) based in UKKK l UR-UCA",
                    "icao": "B738"
                },
                "type": "pax",
                "flightNumber": "85D",
                "free": true,
                "schedule": false,
                "charter": false,
                "payload": {
                    "pax": 152,
                    "cargo": 28,
                    "weights": {
                        "cargo": 2800
                    }
                },
                "depTime": "2026-07-13T08:00:00.000Z",
                "duration": 80,
                "arrTime": "2026-07-13T09:20:00.000Z",
                "depTimeAct": "2026-07-13T08:00:44.673Z",
                "delay": 0,
                "takeoffTimeAct": "2026-07-13T08:09:28.684Z",
                "durationAct": 70,
                "arrTimeAct": "2026-07-13T09:19:48.747Z",
                "open": "2026-07-13T07:36:15.463Z",
                "close": "2026-07-13T09:24:31.801Z",
                "rating": 10,
                "simulator": "msfs2024",
                "network": {
                    "name": null
                },
                "emergency": false,
                "result": {
                    "totals": {
                        "distance": 443,
                        "fuel": 3476,
                        "expenses": 10777,
                        "penalties": 0,
                        "revenue": 23386,
                        "balance": 12609,
                        "prices": {
                            "ticketPrice": 110,
                            "cargoUnitPrice": 132,
                            "costScalars": {
                                "timeAcceleration": 1,
                                "dep": 0.9,
                                "arr": 1,
                                "fuel": 1,
                                "ground": 0.95
                            }
                        },
                        "payload": {
                            "pax": 152,
                            "cargo": 28,
                            "paxByClass": {
                                "F": 4,
                                "C": 15,
                                "Y": 133
                            }
                        }
                    },
                    "expenses": {
                        "fuel": 3930,
                        "aircraft": 5100,
                        "handling": 697,
                        "landing": 1050
                    },
                    "revenue": {
                        "tickets": 19690,
                        "cargo": 3696
                    },
                    "violations": [
                        {
                            "title": "Great touchdown: 1.25G (146 ft/min, challenging  conditions)<br/>Distance from threshold: 455m (accepted range: 173-696m)<br/>Average centerline deviation: 2.43m<br/>Max centerline deviation: 4.77m",
                            "penalty": {
                                "points": 0,
                                "cash": 0
                            },
                            "entry": {
                                "type": "landing",
                                "payload": {
                                    "system": {
                                        "fps": 36
                                    },
                                    "touchDown": {
                                        "gForce": 1.25,
                                        "rate": 146
                                    },
                                    "weather": {
                                        "windDir": 20.41,
                                        "windSpd": 17.09,
                                        "windX": -8.59
                                    }
                                }
                            }
                        }
                    ]
                },
                "createdAt": "2026-07-13T07:09:23.262Z",
                "updatedAt": "2026-07-13T09:24:31.900Z",
                "dep": {
                    "icao": "LGRX",
                    "name": "Patras Araxos Agamemnon Airport",
                    "city": "Patras",
                    "location": {
                        "lat": 38.1511,
                        "lon": 21.4256,
                        "elev": 46
                    }
                },
                "arr": {
                    "icao": "LMML",
                    "name": "Malta International Airport",
                    "city": "Valletta",
                    "location": {
                        "lat": 35.857498,
                        "lon": 14.4775,
                        "elev": 300
                    }
                },
                "actArr": {
                    "icao": "LMML",
                    "name": "Malta International Airport",
                    "city": "Valletta",
                    "location": {
                        "lat": 35.857498,
                        "lon": 14.4775,
                        "elev": 300
                    }
                }
            }
        ]
    }
]