[
    {
        "icao": "NSK",
        "fullname": "Newsky Academy",
        "shortname": "Newsky",
        "countryCode": "PL",
        "stats": {
            "rating": -1,
            "recentFlights": 1535,
            "recentActivePilots": 406,
            "activePilots": 23746,
            "activity": 4,
            "flights": 62282
        }
    },
    {
        "icao": "FNS",
        "fullname": "FanSKY",
        "shortname": "FanSKY",
        "countryCode": "PL",
        "stats": {
            "rating": 9.57,
            "recentFlights": 1317,
            "recentActivePilots": 78,
            "activePilots": 69,
            "activity": 17,
            "flights": 22270
        }
    },
    {
        "icao": "JLY",
        "fullname": "Jet Fly Airways",
        "shortname": "Jet Fly",
        "countryCode": "BR",
        "stats": {
            "rating": 9.49,
            "recentFlights": 964,
            "recentActivePilots": 75,
            "activePilots": 113,
            "activity": 13,
            "flights": 29503
        }
    },
    {
        "icao": "XNO",
        "fullname": "AirNOTT",
        "shortname": "Nott",
        "countryCode": "GB",
        "stats": {
            "rating": 9.49,
            "recentFlights": 961,
            "recentActivePilots": 103,
            "activePilots": 488,
            "activity": 10,
            "flights": 10520
        }
    },
    {
        "icao": "VCP",
        "fullname": "Alpaca Airways",
        "shortname": "Alpaca Airways",
        "countryCode": "GB",
        "stats": {
            "rating": 9.6,
            "recentFlights": 851,
            "recentActivePilots": 101,
            "activePilots": 775,
            "activity": 9,
            "flights": 31665
        }
    },
    {
        "icao": "PDV",
        "fullname": "Pernadovento Virtual Airlines",
        "shortname": "PernaDoVento",
        "countryCode": "BR",
        "stats": {
            "rating": 9.19,
            "recentFlights": 664,
            "recentActivePilots": 48,
            "activePilots": 103,
            "activity": 14,
            "flights": 11286
        }
    },
    {
        "icao": "BVX",
        "fullname": "Osprey Airways",
        "shortname": "Osprey Airways",
        "countryCode": "GB",
        "stats": {
            "rating": 9.04,
            "recentFlights": 628,
            "recentActivePilots": 120,
            "activePilots": 1418,
            "activity": 6,
            "flights": 44267
        }
    },
    {
        "icao": "UKL",
        "fullname": "Ukraine Classic Air Alliance",
        "shortname": "Ukraine Classic",
        "countryCode": "UA",
        "stats": {
            "rating": 9.43,
            "recentFlights": 600,
            "recentActivePilots": 25,
            "activePilots": 54,
            "activity": 24,
            "flights": 1957
        }
    },
    {
        "icao": "BCR",
        "fullname": "Air Robbery Group Ltd",
        "shortname": "Air Robbery",
        "countryCode": "CN",
        "stats": {
            "rating": 8.82,
            "recentFlights": 579,
            "recentActivePilots": 67,
            "activePilots": 115,
            "activity": 9,
            "flights": 1064
        }
    },
    {
        "icao": "TKY",
        "fullname": "TopSKY Airlines",
        "shortname": "TopSKY",
        "countryCode": "PL",
        "stats": {
            "rating": 9.82,
            "recentFlights": 579,
            "recentActivePilots": 45,
            "activePilots": 47,
            "activity": 13,
            "flights": 34975
        }
    },
    {
        "icao": "SWV",
        "fullname": "Skywalk Virtual Airlines",
        "shortname": "SKYWALK",
        "countryCode": "TR",
        "stats": {
            "rating": 9.62,
            "recentFlights": 543,
            "recentActivePilots": 57,
            "activePilots": 98,
            "activity": 10,
            "flights": 28143
        }
    },
    {
        "icao": "EAG",
        "fullname": "Eagle Airlines Virtual",
        "shortname": "Eagle",
        "countryCode": "BR",
        "stats": {
            "rating": 9.5,
            "recentFlights": 498,
            "recentActivePilots": 29,
            "activePilots": 33,
            "activity": 18,
            "flights": 17043
        }
    },
    {
        "icao": "LHG",
        "fullname": "LUFTHANSA GROUP",
        "shortname": "Lufthansa Group",
        "countryCode": "DE",
        "stats": {
            "rating": 9.6,
            "recentFlights": 335,
            "recentActivePilots": 56,
            "activePilots": 958,
            "activity": 6,
            "flights": 30922
        }
    },
    {
        "icao": "ITY",
        "fullname": "ITA AIRWAYS",
        "shortname": "ITA",
        "countryCode": "IT",
        "stats": {
            "rating": 9.24,
            "recentFlights": 289,
            "recentActivePilots": 26,
            "activePilots": 38,
            "activity": 12,
            "flights": 2420
        }
    },
    {
        "icao": "FLX",
        "fullname": "FlyMax Virtual Airlines",
        "shortname": "FlyMax Airlines",
        "countryCode": "BR",
        "stats": {
            "rating": 9.45,
            "recentFlights": 281,
            "recentActivePilots": 21,
            "activePilots": 41,
            "activity": 14,
            "flights": 8552
        }
    },
    {
        "icao": "ACO",
        "fullname": "AEROCOLOMBIA",
        "shortname": "AEROCOLOMBIA",
        "countryCode": "CO",
        "stats": {
            "rating": 9.26,
            "recentFlights": 281,
            "recentActivePilots": 21,
            "activePilots": 31,
            "activity": 14,
            "flights": 4133
        }
    },
    {
        "icao": "GWF",
        "fullname": "Gwiezdna Flota",
        "shortname": "Gwiezdna Flota",
        "countryCode": "PL",
        "stats": {
            "rating": 9.62,
            "recentFlights": 262,
            "recentActivePilots": 15,
            "activePilots": 16,
            "activity": 18,
            "flights": 15713
        }
    },
    {
        "icao": "SRV",
        "fullname": "SURVIVOR TUGA  AIRLINES",
        "shortname": "SURVIVOR",
        "countryCode": "PT",
        "stats": {
            "rating": 9.53,
            "recentFlights": 250,
            "recentActivePilots": 18,
            "activePilots": 33,
            "activity": 14,
            "flights": 4383
        }
    },
    {
        "icao": "AKG",
        "fullname": "AirFrance KLM Group",
        "shortname": "AFKLM",
        "countryCode": "NL",
        "stats": {
            "rating": 9.74,
            "recentFlights": 226,
            "recentActivePilots": 30,
            "activePilots": 36,
            "activity": 8,
            "flights": 5337
        }
    },
    {
        "icao": "BAG",
        "fullname": "British Airways Group",
        "shortname": "BAGroup",
        "countryCode": "GB",
        "stats": {
            "rating": 9.27,
            "recentFlights": 221,
            "recentActivePilots": 29,
            "activePilots": 103,
            "activity": 8,
            "flights": 1922
        }
    },
    {
        "icao": "PEY",
        "fullname": "PEYTER Airlines",
        "shortname": "PEYTER' Partners",
        "countryCode": "PL",
        "stats": {
            "rating": 9.61,
            "recentFlights": 208,
            "recentActivePilots": 17,
            "activePilots": 19,
            "activity": 13,
            "flights": 10600
        }
    },
    {
        "icao": "DKA",
        "fullname": "Sdružení pilotů Die Kapitäne",
        "shortname": "Die Kapitäne air",
        "countryCode": "AT",
        "stats": {
            "rating": 9.59,
            "recentFlights": 207,
            "recentActivePilots": 12,
            "activePilots": 15,
            "activity": 18,
            "flights": 3498
        }
    },
    {
        "icao": "VNV",
        "fullname": "VNAVPL Airlines",
        "shortname": "VNAVPL",
        "countryCode": "PL",
        "stats": {
            "rating": 9.16,
            "recentFlights": 205,
            "recentActivePilots": 12,
            "activePilots": 23,
            "activity": 18,
            "flights": 1568
        }
    },
    {
        "icao": "AFS",
        "fullname": "Akademia FanSKY",
        "shortname": "AFS",
        "countryCode": "PL",
        "stats": {
            "rating": 9.06,
            "recentFlights": 204,
            "recentActivePilots": 31,
            "activePilots": 77,
            "activity": 7,
            "flights": 3873
        }
    },
    {
        "icao": "JTG",
        "fullname": "Jet Team Global Air Charter Company",
        "shortname": "Jet Team",
        "countryCode": "US",
        "stats": {
            "rating": 10,
            "recentFlights": 199,
            "recentActivePilots": 4,
            "activePilots": 4,
            "activity": 50,
            "flights": 5682
        }
    },
    {
        "icao": "LOT",
        "fullname": "LOT Polish Airlines",
        "shortname": "PLL LOT",
        "countryCode": "PL",
        "stats": {
            "rating": 8.99,
            "recentFlights": 169,
            "recentActivePilots": 30,
            "activePilots": 164,
            "activity": 6,
            "flights": 6032
        }
    },
    {
        "icao": "UEA",
        "fullname": "United Virtual Airlines",
        "shortname": "United",
        "countryCode": "US",
        "stats": {
            "rating": 8.87,
            "recentFlights": 156,
            "recentActivePilots": 18,
            "activePilots": 21,
            "activity": 9,
            "flights": 214
        }
    },
    {
        "icao": "FCN",
        "fullname": "Virtual Wings Airlines",
        "shortname": "Virtual Wings",
        "countryCode": "CO",
        "stats": {
            "rating": 9.28,
            "recentFlights": 155,
            "recentActivePilots": 7,
            "activePilots": 13,
            "activity": 23,
            "flights": 4790
        }
    },
    {
        "icao": "CPZ",
        "fullname": "Compass Atlantic",
        "shortname": "Compass",
        "countryCode": "US",
        "stats": {
            "rating": 9.39,
            "recentFlights": 155,
            "recentActivePilots": 9,
            "activePilots": 15,
            "activity": 18,
            "flights": 437
        }
    },
    {
        "icao": "NOO",
        "fullname": "NOVA",
        "shortname": "NOVA",
        "countryCode": "CO",
        "stats": {
            "rating": 9.65,
            "recentFlights": 152,
            "recentActivePilots": 14,
            "activePilots": 23,
            "activity": 11,
            "flights": 6386
        }
    }
]