{
  "results": [
    {
      "_id": "6a57932d5760ec7cdbf950d5",
      "pilot": {
        "_id": "69db5c78997a4751ff8a1806",
        "fullname": "Mozhehov Denys"
      },
      "aircraft": {
        "airframe": {
          "ident": "B77W",
          "icao": "B77W",
          "icon": "B777",
          "name": "Boeing 777-300ER"
        }
      },
      "airline": {
        "_id": "695810be3dc76275ba8befa9",
        "icao": "UKL",
        "fullname": "Ukraine Classic Air Alliance",
        "logo": "695810be3dc76275ba8befa91781451227917"
      },
      "schedule": true,
      "type": "pax",
      "flightNumber": "2915",
      "depTimeAct": "2026-07-15T14:13:03.775Z",
      "arrTimeAct": null,
      "simulator": "msfs",
      "network": {
        "name": null,
        "pings": 0,
        "pingsTotal": 6,
        "ratio": 0,
        "lastPing": null
      },
      "version": "0.0.741",
      "lastState": {
        "location": {
          "lat": 46.727019017768,
          "lon": 28.645499879416,
          "hdg": 207.4
        }
      },
      "emergency": false,
      "dep": {
        "icao": "LUKK",
        "name": "Chişinău International Airport"
      },
      "arr": {
        "icao": "LTFM",
        "name": "İstanbul Airport"
      },
      "charter": false
    },
    {
      "_id": "6a5774315760ec7cdbf6977a",
      "pilot": {
        "_id": "6a4e58ae5760ec7cdb4bd83a",
        "fullname": "Nick Star"
      },
      "aircraft": {
        "airframe": {
          "ident": "A20N",
          "icao": "A20N",
          "icon": "A320",
          "name": "Airbus A320 neo"
        }
      },
      "airline": {
        "_id": "695810be3dc76275ba8befa9",
        "icao": "UKL",
        "fullname": "Ukraine Classic Air Alliance",
        "logo": "695810be3dc76275ba8befa91781451227917"
      },
      "type": "pax",
      "flightNumber": "4745",
      "depTimeAct": "2026-07-15T12:25:15.312Z",
      "arrTimeAct": null,
      "simulator": "msfs",
      "network": {
        "name": null,
        "pings": 0,
        "pingsTotal": 120,
        "ratio": 0,
        "lastPing": null
      },
      "version": "0.0.741",
      "lastState": {
        "location": {
          "lat": 50.216314752792,
          "lon": 29.666702585983,
          "hdg": 62.7
        }
      },
      "emergency": false,
      "dep": {
        "icao": "EKCH",
        "name": "Copenhagen Kastrup Airport"
      },
      "arr": {
        "icao": "UKBB",
        "name": "Boryspil International Airport"
      },
      "schedule": false,
      "charter": false
    }
  ],
  "totalResults": 2
}