{
  "results": [
    {
      "_id": "6a48e8ed5760ec7cdbdbbe81",
      "pilot": {
        "_id": "653037e6139a4e9a333116c1",
        "fullname": "Roman Zavialov"
      },
      "aircraft": {
        "airframe": {
          "ident": "B738",
          "icao": "B738",
          "icon": "B738",
          "name": "Boeing 737-800"
        }
      },
      "airline": {
        "_id": "695810be3dc76275ba8befa9",
        "icao": "UKL",
        "fullname": "Ukraine Classic Air Alliance",
        "logo": "695810be3dc76275ba8befa91781451227917"
      },
      "type": "pax",
      "flightNumber": "6001",
      "depTimeAct": "2026-07-04T11:37:51.382Z",
      "arrTimeAct": null,
      "simulator": "msfs2024",
      "network": {
        "name": "vatsim",
        "pings": 18,
        "pingsTotal": 18,
        "ratio": 1,
        "lastPing": "2026-07-04T11:52:03.031Z"
      },
      "version": "0.0.727",
      "lastState": {
        "location": {
          "lat": 35.951354896656,
          "lon": 24.899094987787,
          "hdg": 336.4
        }
      },
      "emergency": false,
      "dep": {
        "icao": "LGIR",
        "name": "Heraklion International Nikos Kazantzakis Airport"
      },
      "arr": {
        "icao": "UKBB",
        "name": "Boryspil International Airport"
      },
      "schedule": false,
      "charter": false
    },
    {
      "_id": "6a48e1db5760ec7cdbdaebb2",
      "pilot": {
        "_id": "695807ad3dc76275ba8a6e4b",
        "fullname": "Alex Zaugarov"
      },
      "aircraft": {
        "airframe": {
          "ident": "A21N",
          "icao": "A21N",
          "icon": "A320",
          "name": "Airbus A321 neo"
        }
      },
      "airline": {
        "_id": "695810be3dc76275ba8befa9",
        "icao": "UKL",
        "fullname": "Ukraine Classic Air Alliance",
        "logo": "695810be3dc76275ba8befa91781451227917"
      },
      "type": "pax",
      "flightNumber": "411M",
      "depTimeAct": "2026-07-04T11:05:31.514Z",
      "arrTimeAct": null,
      "simulator": "xp",
      "network": {
        "name": "vatsim",
        "pings": 57,
        "pingsTotal": 59,
        "ratio": 0.9661016949152542,
        "lastPing": "2026-07-04T11:52:03.031Z"
      },
      "version": "0.0.727",
      "lastState": {
        "location": {
          "lat": 49.946838,
          "lon": 21.115318,
          "hdg": 111.1
        }
      },
      "emergency": false,
      "dep": {
        "icao": "EDDB",
        "name": "Berlin Brandenburg Airport"
      },
      "arr": {
        "icao": "UKLN",
        "name": "Chernivtsi International Airport"
      },
      "schedule": false,
      "charter": false
    },
    {
      "_id": "6a48db0a5760ec7cdbda0968",
      "pilot": {
        "_id": "695ce1b43dc76275ba0f240e",
        "fullname": "Nazar Pilot"
      },
      "aircraft": {
        "airframe": {
          "ident": "B772",
          "icao": "B772",
          "icon": "B777",
          "name": "Boeing 777-200ER"
        }
      },
      "airline": {
        "_id": "695810be3dc76275ba8befa9",
        "icao": "UKL",
        "fullname": "Ukraine Classic Air Alliance",
        "logo": "695810be3dc76275ba8befa91781451227917"
      },
      "type": "pax",
      "flightNumber": "1204",
      "depTimeAct": "2026-07-04T10:25:23.338Z",
      "arrTimeAct": null,
      "simulator": "msfs",
      "network": {
        "name": "vatsim",
        "pings": 96,
        "pingsTotal": 99,
        "ratio": 0.9696969696969697,
        "lastPing": "2026-07-04T11:52:03.030Z"
      },
      "version": "0.0.727",
      "lastState": {
        "location": {
          "lat": 45.900095539084,
          "lon": 30.521555552832,
          "hdg": 15.1
        }
      },
      "emergency": false,
      "dep": {
        "icao": "LTAI",
        "name": "Antalya International Airport"
      },
      "arr": {
        "icao": "UKBB",
        "name": "Boryspil International Airport"
      },
      "schedule": false,
      "charter": false
    },
    {
      "_id": "6a48df405760ec7cdbda98eb",
      "pilot": {
        "_id": "69778f513dc76275bad73f10",
        "fullname": "Puero Dim"
      },
      "aircraft": {
        "airframe": {
          "ident": "B38M",
          "icao": "B38M",
          "icon": "B738",
          "name": "Boeing 737 MAX 8"
        }
      },
      "airline": {
        "_id": "695810be3dc76275ba8befa9",
        "icao": "UKL",
        "fullname": "Ukraine Classic Air Alliance",
        "logo": "695810be3dc76275ba8befa91781451227917"
      },
      "type": "pax",
      "flightNumber": "096W",
      "depTimeAct": "2026-07-04T11:14:33.444Z",
      "arrTimeAct": null,
      "simulator": "msfs2024",
      "network": {
        "name": null,
        "pings": 0,
        "pingsTotal": 67,
        "ratio": 0,
        "lastPing": null
      },
      "version": "0.0.727",
      "lastState": {
        "location": {
          "lat": 39.524719478952,
          "lon": 32.446314529527,
          "hdg": 18
        }
      },
      "emergency": false,
      "dep": {
        "icao": "LTAI",
        "name": "Antalya International Airport"
      },
      "arr": {
        "icao": "UKOO",
        "name": "Odessa International Airport"
      },
      "schedule": false,
      "charter": false
    },
    {
      "_id": "6a48eca16748d36670d31994",
      "pilot": {
        "_id": "69c3ced7c739a30ec89bfda3",
        "fullname": "Yury Tr"
      },
      "aircraft": {
        "airframe": {
          "ident": "A388",
          "icao": "A388",
          "icon": "A380",
          "name": "Airbus A380"
        }
      },
      "airline": {
        "_id": "695810be3dc76275ba8befa9",
        "icao": "UKL",
        "fullname": "Ukraine Classic Air Alliance",
        "logo": "695810be3dc76275ba8befa91781451227917"
      },
      "type": "pax",
      "flightNumber": "55K",
      "depTimeAct": "2026-07-04T11:45:51.388Z",
      "arrTimeAct": null,
      "simulator": "msfs2024",
      "network": {
        "name": null,
        "pings": 0,
        "pingsTotal": 7,
        "ratio": 0,
        "lastPing": null
      },
      "version": "0.0.739",
      "lastState": {
        "location": {
          "lat": 27.28237246367,
          "lon": 33.766790891362,
          "hdg": 341.2
        }
      },
      "emergency": false,
      "dep": {
        "icao": "HEGN",
        "name": "Hurghada International Airport"
      },
      "arr": {
        "icao": "UKLL",
        "name": "Lviv International Airport"
      },
      "schedule": false,
      "charter": false
    }
  ],
  "totalResults": 5
}