{
  "results": [
    {
      "_id": "6a55089f5760ec7cdbcc3a42",
      "pilot": {
        "_id": "6962a0523dc76275baa3b19c",
        "fullname": "Silver-DK"
      },
      "aircraft": {
        "airframe": {
          "ident": "B772",
          "icao": "B772",
          "icon": "B777",
          "name": "Boeing 777-200ER"
        }
      },
      "airline": {
        "_id": "695810be3dc76275ba8befa9",
        "icao": "UKL",
        "fullname": "Ukraine Classic Air Alliance",
        "logo": "695810be3dc76275ba8befa91781451227917"
      },
      "schedule": true,
      "type": "pax",
      "flightNumber": "243",
      "depTimeAct": "2026-07-13T16:05:57.242Z",
      "arrTimeAct": null,
      "simulator": "msfs2024",
      "network": {
        "name": null,
        "pings": 0,
        "pingsTotal": 334,
        "ratio": 0,
        "lastPing": null
      },
      "version": "0.0.741",
      "lastState": {
        "location": {
          "lat": 20.747393054727,
          "lon": 66.810194673473,
          "hdg": 115.3
        }
      },
      "emergency": false,
      "dep": {
        "icao": "UKBB",
        "name": "Boryspil International Airport"
      },
      "arr": {
        "icao": "VCBI",
        "name": "Bandaranaike International Colombo Airport"
      },
      "charter": false
    },
    {
      "_id": "6a554be35760ec7cdbd30ee2",
      "pilot": {
        "_id": "69778f513dc76275bad73f10",
        "fullname": "Puero Dim"
      },
      "aircraft": {
        "airframe": {
          "ident": "B38M",
          "icao": "B38M",
          "icon": "B738",
          "name": "Boeing 737 MAX 8"
        }
      },
      "airline": {
        "_id": "695810be3dc76275ba8befa9",
        "icao": "UKL",
        "fullname": "Ukraine Classic Air Alliance",
        "logo": "695810be3dc76275ba8befa91781451227917"
      },
      "charter": true,
      "type": "pax",
      "flightNumber": "30G",
      "depTimeAct": "2026-07-13T21:10:59.961Z",
      "arrTimeAct": null,
      "simulator": "msfs2024",
      "network": {
        "name": null,
        "pings": 0,
        "pingsTotal": 53,
        "ratio": 0,
        "lastPing": null
      },
      "version": "0.0.741",
      "lastState": {
        "location": {
          "lat": -37.391380905546,
          "lon": -60.976121797772,
          "hdg": 28.6
        }
      },
      "emergency": false,
      "dep": {
        "icao": "SAZB",
        "name": "Comandante Espora Airport"
      },
      "arr": {
        "icao": "SAEZ",
        "name": "Minister Pistarini International Airport"
      },
      "schedule": false
    }
  ],
  "totalResults": 2
}