{
  "results": [
    {
      "_id": "6a5bcc2350c8a562fc8691ac",
      "pilot": {
        "_id": "6962a0523dc76275baa3b19c",
        "fullname": "Silver-DK"
      },
      "aircraft": {
        "airframe": {
          "ident": "A320",
          "icao": "A320",
          "icon": "A320",
          "name": "Airbus A320"
        }
      },
      "airline": {
        "_id": "695810be3dc76275ba8befa9",
        "icao": "UKL",
        "fullname": "Ukraine Classic Air Alliance",
        "logo": "695810be3dc76275ba8befa91781451227917"
      },
      "schedule": true,
      "type": "pax",
      "flightNumber": "2810",
      "depTimeAct": "2026-07-18T19:17:24.789Z",
      "arrTimeAct": null,
      "simulator": "msfs2024",
      "network": {
        "name": null,
        "pings": 0,
        "pingsTotal": 89,
        "ratio": 0,
        "lastPing": null
      },
      "version": "0.0.741",
      "lastState": {
        "location": {
          "lat": 48.941358263379,
          "lon": 26.42518332689,
          "hdg": 87.3
        }
      },
      "emergency": false,
      "dep": {
        "icao": "EDDM",
        "name": "Munich Airport"
      },
      "arr": {
        "icao": "UKCC",
        "name": "Donetsk Sergei Prokofiev International Airport"
      },
      "charter": false
    },
    {
      "_id": "6a5bdfae50c8a562fc88a666",
      "pilot": {
        "_id": "6969fd073dc76275ba58551f",
        "fullname": "Illia Mendelis"
      },
      "aircraft": {
        "airframe": {
          "ident": "B738",
          "icao": "B738",
          "icon": "B738",
          "name": "Boeing 737-800"
        }
      },
      "airline": {
        "_id": "695810be3dc76275ba8befa9",
        "icao": "UKL",
        "fullname": "Ukraine Classic Air Alliance",
        "logo": "695810be3dc76275ba8befa91781451227917"
      },
      "type": "pax",
      "flightNumber": "0711",
      "depTimeAct": "2026-07-18T20:37:20.537Z",
      "arrTimeAct": null,
      "simulator": "xp",
      "network": {
        "name": null,
        "pings": 0,
        "pingsTotal": 17,
        "ratio": 0,
        "lastPing": null
      },
      "version": "0.0.741",
      "lastState": {
        "location": {
          "lat": 49.925514,
          "lon": 36.274601,
          "hdg": 82.1
        }
      },
      "emergency": false,
      "dep": {
        "icao": "UKHH",
        "name": "Kharkiv International Airport"
      },
      "arr": {
        "icao": "UKOO",
        "name": "Odessa International Airport"
      },
      "schedule": false,
      "charter": false
    },
    {
      "_id": "6a5bc9e550c8a562fc8655b3",
      "pilot": {
        "_id": "6a4a3a585760ec7cdbf933ff",
        "fullname": "Serhii Petrovich"
      },
      "aircraft": {
        "airframe": {
          "ident": "A320",
          "icao": "A320",
          "icon": "A320",
          "name": "Airbus A320"
        }
      },
      "airline": {
        "_id": "695810be3dc76275ba8befa9",
        "icao": "UKL",
        "fullname": "Ukraine Classic Air Alliance",
        "logo": "695810be3dc76275ba8befa91781451227917"
      },
      "type": "pax",
      "flightNumber": "723Z",
      "depTimeAct": "2026-07-18T19:07:01.625Z",
      "arrTimeAct": null,
      "simulator": "xp",
      "network": {
        "name": null,
        "pings": 0,
        "pingsTotal": 92,
        "ratio": 0,
        "lastPing": null
      },
      "version": "0.0.741",
      "lastState": {
        "location": {
          "lat": 47.080826,
          "lon": 16.552879,
          "hdg": 250.5
        }
      },
      "emergency": false,
      "dep": {
        "icao": "UKBB",
        "name": "Boryspil International Airport"
      },
      "arr": {
        "icao": "EDJA",
        "name": "Memmingen Allgau Airport"
      },
      "schedule": false,
      "charter": false
    }
  ],
  "totalResults": 3
}